{
  "posts": [
    {
      "id": 5,
      "title": "DEDEDEDE",
      "body": "someBodyOnceToldMe 5"
    },
    {
      "id": 6,
      "title": "json-server6",
      "body": "someBodyOnceToldMe 6"
    },
    {
      "id": 7,
      "title": "json-server7",
      "body": "someBodyOnceToldMe 7"
    },
    {
      "id": 8,
      "title": "json-server8",
      "body": "someBodyOnceToldMe 8"
    },
    {
      "id": 9,
      "title": "json-server9",
      "body": "someBodyOnceToldMe 9"
    },
    {
      "title": "aaaaaaaaaaaaaaaaaaaaaaaaaaaaaaaaaaaaaaaaaaaa",
      "body": "aaaaaaaaaaaaaaaaaaaaaaaaaaaaaaaaaaaaaaaaaaaa",
      "id": 10
    },
    {
      "title": "bbbbb",
      "body": "bbbbb",
      "id": 11
    },
    {
      "title": "ccccccc",
      "body": "ccccccc",
      "id": 12
    }
  ]
}